BUILD.rst
CHANGES.rst
COPYRIGHT.txt
INSTALL.rst
LICENSE.txt
MANIFEST.in
README.rst
SELENIUM_COPYRIGHT.txt
requirements-dev.txt
requirements.txt
setup.cfg
setup.py
docs/Selenium2Library.html
src/Selenium2Library/__init__.py
src/Selenium2Library/version.py
src/Selenium2Library/webdrivermonkeypatches.py
src/Selenium2Library/keywords/__init__.py
src/Selenium2Library/keywords/_alert.py
src/Selenium2Library/keywords/_browsermanagement.py
src/Selenium2Library/keywords/_cookie.py
src/Selenium2Library/keywords/_element.py
src/Selenium2Library/keywords/_formelement.py
src/Selenium2Library/keywords/_javascript.py
src/Selenium2Library/keywords/_logging.py
src/Selenium2Library/keywords/_runonfailure.py
src/Selenium2Library/keywords/_screenshot.py
src/Selenium2Library/keywords/_selectelement.py
src/Selenium2Library/keywords/_tableelement.py
src/Selenium2Library/keywords/_waiting.py
src/Selenium2Library/keywords/keywordgroup.py
src/Selenium2Library/locators/__init__.py
src/Selenium2Library/locators/customlocator.py
src/Selenium2Library/locators/elementfinder.py
src/Selenium2Library/locators/tableelementfinder.py
src/Selenium2Library/locators/windowmanager.py
src/Selenium2Library/resources/firefoxprofile/localstore.rdf
src/Selenium2Library/resources/firefoxprofile/prefs.js
src/Selenium2Library/utils/__init__.py
src/Selenium2Library/utils/browsercache.py
src/Selenium2Library/utils/librarylistener.py
src/Selenium2Library/utils/events/__init__.py
src/Selenium2Library/utils/events/event.py
src/Selenium2Library/utils/events/scope_event.py
src/robotframework_selenium2library_divfor.egg-info/PKG-INFO
src/robotframework_selenium2library_divfor.egg-info/SOURCES.txt
src/robotframework_selenium2library_divfor.egg-info/dependency_links.txt
src/robotframework_selenium2library_divfor.egg-info/requires.txt
src/robotframework_selenium2library_divfor.egg-info/top_level.txt