Metadata-Version: 1.1
Name: robotframework-selenium2library-divfor
Version: 1.8.0.1
Summary: Web testing library for Robot Framework with locator wrapper feature
Home-page: https://github.com/divfor/Selenium2Library
Author: Fred Huang
Author-email: divfor@gmail.com
License: Apache License 2.0
Keywords: robotframework testing testautomation selenium selenium2 webdriver web
Platform: any
Classifier: Development Status :: 5 - Production/Stable
Classifier: License :: OSI Approved :: Apache Software License
Classifier: Operating System :: OS Independent
Classifier: Programming Language :: Python
Classifier: Topic :: Software Development :: Testing
